LICENSE
README.md
pyproject.toml
setup.py
Tuser/Concierge.py
Tuser/__init__.py
Tuser/tuser.py
Ziplit.Tuser.egg-info/PKG-INFO
Ziplit.Tuser.egg-info/SOURCES.txt
Ziplit.Tuser.egg-info/dependency_links.txt
Ziplit.Tuser.egg-info/top_level.txt